grepy/__init__.py
grepy/grepy.py
grepy_tool-0.1.0.dist-info/licenses/LICENSE.txt
grepy_tool-0.1.0.dist-info/METADATA
grepy_tool-0.1.0.dist-info/WHEEL
grepy_tool-0.1.0.dist-info/entry_points.txt
grepy_tool-0.1.0.dist-info/top_level.txt
grepy_tool-0.1.0.dist-info/RECORD
