Metadata-Version: 2.4
Name: grepy-tool
Version: 0.1.0
Summary: An enhanced grep-like tool
Home-page: https://github.com/prabhkesar123/grepy
Author: Prabh-Kesar
Author-email: lolcodelang@gmail.com
Classifier: Programming Language :: Python :: 3
Classifier: License :: OSI Approved :: MIT License
Classifier: Operating System :: OS Independent
Requires-Python: >=3.6
License-File: LICENSE.txt
Requires-Dist: colorama>=0.4.4
Dynamic: author
Dynamic: author-email
Dynamic: classifier
Dynamic: description
Dynamic: description-content-type
Dynamic: home-page
Dynamic: license-file
Dynamic: requires-dist
Dynamic: requires-python
Dynamic: summary
